tensordiff/__init__.py
tensordiff/_version.py
tensordiff/coefs.py
tensordiff/diff.py
tensordiff/grids.py
tensordiff/operators.py
tensordiff/pde.py
tensordiff/stencils.py
tensordiff/utils.py
tensordiff/vector.py
test/__init__.py
test/test_bugs.py
test/test_coefs.py
test/test_diff.py
test/test_findiff.py
test/test_grids.py
test/test_pde.py
test/test_scaling.py
test/test_utils.py
test/test_vector.py
tensordiff-10.1.dist-info/LICENSE
tensordiff-10.1.dist-info/METADATA
tensordiff-10.1.dist-info/WHEEL
tensordiff-10.1.dist-info/top_level.txt
tensordiff-10.1.dist-info/RECORD
