Metadata-Version: 2.1
Name: tensordiff
Version: 10.1
Summary: A Python package for finite difference derivatives in any number of dimensions.
Home-page: https://github.com/AdwardAllan/tensordiff.git
Author: Adwardallan
Author-email: 66543119+AdwardAllan@users.noreply.github.com
License: MIT
Keywords: finite-differences,numerical-derivatives,scientific-computing
Platform: ALL
Classifier: Intended Audience :: Developers
Classifier: Topic :: Scientific/Engineering :: Mathematics
Classifier: License :: OSI Approved :: MIT License
Classifier: Programming Language :: Python :: 3
Classifier: Programming Language :: Python :: 3.4
Classifier: Programming Language :: Python :: 3.5
Classifier: Programming Language :: Python :: 3.6
Classifier: Programming Language :: Python :: 3.7
Classifier: Programming Language :: Python :: 3.8
Classifier: Programming Language :: Python :: 3.9
License-File: LICENSE
